twicorder/__init__.py
twicorder/aio_auth.py
twicorder/appdata.py
twicorder/cached_users.py
twicorder/config.py
twicorder/constants.py
twicorder/controller.py
twicorder/exceptions.py
twicorder/exchange.py
twicorder/logger.py
twicorder/rate_limits.py
twicorder/utils.py
twicorder/exporters/__init__.py
twicorder/exporters/follower_ids.py
twicorder/queries/__init__.py
twicorder/queries/base.py
twicorder/queries/request/__init__.py
twicorder/queries/request/base.py
twicorder/queries/request/production.py
twicorder/queries/request/request_queries.py
twicorder/queries/request/tweet.py
twicorder/queries/request/endpoints/__init__.py
twicorder/queries/request/endpoints/follower_id.py
twicorder/queries/request/endpoints/friends_list.py
twicorder/queries/request/endpoints/fullarchive_get.py
twicorder/queries/request/endpoints/fullarchive_post.py
twicorder/queries/request/endpoints/rate_limit_status.py
twicorder/queries/request/endpoints/standard_search.py
twicorder/queries/request/endpoints/status.py
twicorder/queries/request/endpoints/timeline.py
twicorder/queries/request/endpoints/user_lookup.py
twicorder/tasks/__init__.py
twicorder/tasks/manager.py
twicorder/tasks/task.py
twicorder/tasks/generators/__init__.py
twicorder/tasks/generators/base_generator.py
twicorder/tasks/generators/config_generator.py
twicorder/tasks/generators/timeline_generator.py
twicorder/tasks/generators/user_lookup_generator.py
twicorder_search-0.3.0.data/scripts/twicorder
twicorder_search-0.3.0.dist-info/LICENSE
twicorder_search-0.3.0.dist-info/METADATA
twicorder_search-0.3.0.dist-info/WHEEL
twicorder_search-0.3.0.dist-info/top_level.txt
twicorder_search-0.3.0.dist-info/RECORD
