Metadata-Version: 2.1
Name: twicorder-search
Version: 0.3.0
Summary: A Twitter crawler for Python 3 based on Twitter's public API
Home-page: https://github.com/thimic/twicorder-search
Author: Michael Thingnes
Author-email: thimic@gmail.com
License: MIT
Download-URL: https://github.com/thimic/twicorder-search/archive/v0.3.0.tar.gz
Project-URL: Bug Tracker, https://github.com/thimic/twicorder-search/issues
Keywords: twitter,crawler,research
Platform: UNKNOWN
Classifier: Programming Language :: Python :: 3
Classifier: License :: OSI Approved :: MIT License
Classifier: Operating System :: OS Independent
Requires-Python: >=3.7
License-File: LICENSE
Requires-Dist: Authlib (~=0.14.3)
Requires-Dist: PyYAML (~=5.1)
Requires-Dist: aiosqlite (~=0.13.0)
Requires-Dist: asyncclick (~=7.0.9)
Requires-Dist: asyncio (~=3.4.3)
Requires-Dist: click (~=7.1.2)
Requires-Dist: httpx (~=0.13.3)
